robin_sd_download/__init__.py
robin_sd_download/__main__.py
robin_sd_download/_version.py
robin_sd_download/api_interaction/__init__.py
robin_sd_download/api_interaction/get_bearer_token.py
robin_sd_download/api_interaction/get_software.py
robin_sd_download/api_interaction/get_software_info.py
robin_sd_download/apt_interaction/__init__.py
robin_sd_download/apt_interaction/ensure_hook.py
robin_sd_download/apt_interaction/ensure_local_repo.py
robin_sd_download/apt_interaction/offline_install.py
robin_sd_download/apt_interaction/prepare_install.py
robin_sd_download/slack_interaction/__init__.py
robin_sd_download/slack_interaction/slack_handler.py
robin_sd_download/supportive_scripts/__init__.py
robin_sd_download/supportive_scripts/arg_parse.py
robin_sd_download/supportive_scripts/logger.py
robin_sd_download/supportive_scripts/sudo_file.py
robin_sd_download/supportive_scripts/version_checker.py
robin_sd_download/supportive_scripts/yaml_parser.py
tests/__init__.py
tests/test.py
robin_sd_download-0.4.2.dist-info/METADATA
robin_sd_download-0.4.2.dist-info/WHEEL
robin_sd_download-0.4.2.dist-info/entry_points.txt
robin_sd_download-0.4.2.dist-info/top_level.txt
robin_sd_download-0.4.2.dist-info/RECORD
