Metadata-Version: 2.1
Name: robin-sd-download
Version: 0.4.2
Summary: Package to download files to the Robin Radar API
Home-page: https://bitbucket.org/robin-radar-systems/sd-api-download-pip-package.git
Author: Robin Radar Systems
Author-email: devops@robinradar.com
License: MIT
Keywords: python,robin,radar,download,software,sd
Requires-Dist: validators
Requires-Dist: requests
Requires-Dist: pyYAML
Requires-Dist: zipfile36
Requires-Dist: slack-sdk
Requires-Dist: pypi-simple
